PyEGRO/__init__.py
PyEGRO/doe/__init__.py
PyEGRO/doe/initial_design.py
PyEGRO/doe/sampling.py
PyEGRO/meta/__init__.py
PyEGRO/meta/cokriging/__init__.py
PyEGRO/meta/cokriging/cokriging.py
PyEGRO/meta/cokriging/cokriging_utils.py
PyEGRO/meta/cokriging/examples.py
PyEGRO/meta/cokriging/visualization.py
PyEGRO/meta/egocokriging/__init__.py
PyEGRO/meta/egocokriging/acquisition.py
PyEGRO/meta/egocokriging/config.py
PyEGRO/meta/egocokriging/model.py
PyEGRO/meta/egocokriging/training.py
PyEGRO/meta/egocokriging/utils.py
PyEGRO/meta/egocokriging/visualization.py
PyEGRO/meta/egogpr/__init__.py
PyEGRO/meta/egogpr/acquisition.py
PyEGRO/meta/egogpr/config.py
PyEGRO/meta/egogpr/model.py
PyEGRO/meta/egogpr/training.py
PyEGRO/meta/egogpr/utils.py
PyEGRO/meta/egogpr/visualization.py
PyEGRO/meta/evaluation/__init__.py
PyEGRO/meta/evaluation/modeltesting.py
PyEGRO/meta/gpr/__init__.py
PyEGRO/meta/gpr/examples.py
PyEGRO/meta/gpr/gpr.py
PyEGRO/meta/gpr/gpr_utils.py
PyEGRO/meta/gpr/visualization.py
PyEGRO/optimize/GA.py
PyEGRO/optimize/__init__.py
PyEGRO/robustopt/__init__.py
PyEGRO/robustopt/visualization.py
PyEGRO/robustopt/method_mcs/__init__.py
PyEGRO/robustopt/method_mcs/mcs.py
PyEGRO/robustopt/method_nnmcs/__init__.py
PyEGRO/robustopt/method_nnmcs/_ann_hyperopt.py
PyEGRO/robustopt/method_nnmcs/_ann_training.py
PyEGRO/robustopt/method_nnmcs/_multi_obj_two_stage.py
PyEGRO/robustopt/method_nnmcs/nnmcs.py
PyEGRO/robustopt/method_pce/__init__.py
PyEGRO/robustopt/method_pce/pce.py
PyEGRO/sensitivity/__init__.py
PyEGRO/sensitivity/SAmcs/__init__.py
PyEGRO/sensitivity/SAmcs/samcs.py
PyEGRO/sensitivity/SApce/__init__.py
PyEGRO/sensitivity/SApce/sapce.py
PyEGRO/uncertainty/__init__.py
PyEGRO/uncertainty/UQmcs/__init__.py
PyEGRO/uncertainty/UQmcs/_uqmcs.py
PyEGRO/uncertainty/UQmcs/uqmcs.py
PyEGRO/uncertainty/UQmcs/visualization.py
pyegro-0.2.1.dist-info/licenses/LICENSE
pyegro-0.2.1.dist-info/METADATA
pyegro-0.2.1.dist-info/WHEEL
pyegro-0.2.1.dist-info/top_level.txt
pyegro-0.2.1.dist-info/RECORD
